vera_syntaxis/__init__.py
vera_syntaxis/call_graph.py
vera_syntaxis/cli.py
vera_syntaxis/config.py
vera_syntaxis/file_discovery.py
vera_syntaxis/linter_base.py
vera_syntaxis/linters.py
vera_syntaxis/parser.py
vera_syntaxis/symbol_table.py
vera_syntaxis/violations.py
vera_syntaxis/visitor.py
vera_syntaxis/gui/__init__.py
vera_syntaxis/gui/launch_gui.py
vera_syntaxis/gui/controller/__init__.py
vera_syntaxis/gui/controller/app_controller.py
vera_syntaxis/gui/model/__init__.py
vera_syntaxis/gui/model/analysis_model.py
vera_syntaxis/gui/model/preferences.py
vera_syntaxis/gui/model/report_generator.py
vera_syntaxis/gui/view/__init__.py
vera_syntaxis/gui/view/config_editor.py
vera_syntaxis/gui/view/main_window.py
vera_syntaxis/gui/view/menu_bar.py
vera_syntaxis/gui/view/progress_dialog.py
vera_syntaxis/gui/view/report_tabs.py
vera_syntaxis/gui/view/status_bar.py
vera_syntaxis/gui/view/text_highlighter.py
vera_syntaxis/gui/view/toolbar.py
vera_syntaxis/linters/__init__.py
vera_syntaxis/linters/circular_dependency.py
vera_syntaxis/linters/data_clump.py
vera_syntaxis/linters/feature_envy.py
vera_syntaxis/linters/god_object.py
vera_syntaxis/linters/mvbc.py
vera_syntaxis/linters/tight_coupling.py
vera_syntaxis/pattern_detectors/__init__.py
vera_syntaxis/pattern_detectors/adapter_detector.py
vera_syntaxis/pattern_detectors/base.py
vera_syntaxis/pattern_detectors/decorator_detector.py
vera_syntaxis/pattern_detectors/factory_detector.py
vera_syntaxis/pattern_detectors/observer_detector.py
vera_syntaxis/pattern_detectors/singleton_detector.py
vera_syntaxis/pattern_detectors/strategy_detector.py
vera_syntaxis-0.1.0.dist-info/licenses/LICENSE
vera_syntaxis-0.1.0.dist-info/METADATA
vera_syntaxis-0.1.0.dist-info/WHEEL
vera_syntaxis-0.1.0.dist-info/entry_points.txt
vera_syntaxis-0.1.0.dist-info/top_level.txt
vera_syntaxis-0.1.0.dist-info/RECORD
