Metadata-Version: 2.4
Name: vera-syntaxis
Version: 0.1.0
Summary: A static analysis tool for detecting architectural code smells in Python
Author: RH Labs/The SurveyOS Project
License: MIT
Project-URL: Homepage, https://github.com/yourusername/vera-syntaxis
Project-URL: Bug Tracker, https://github.com/yourusername/vera-syntaxis/issues
Keywords: linter,architecture,code-quality,static-analysis,design-patterns
Classifier: Development Status :: 3 - Alpha
Classifier: Intended Audience :: Developers
Classifier: Topic :: Software Development :: Quality Assurance
Classifier: Topic :: Software Development :: Testing
Classifier: Programming Language :: Python :: 3
Classifier: Programming Language :: Python :: 3.8
Classifier: Programming Language :: Python :: 3.9
Classifier: Programming Language :: Python :: 3.10
Classifier: Programming Language :: Python :: 3.11
Classifier: Programming Language :: Python :: 3.12
Classifier: License :: OSI Approved :: MIT License
Classifier: Operating System :: OS Independent
Requires-Python: >=3.8
License-File: LICENSE
Requires-Dist: networkx>=2.8
Requires-Dist: pydantic>=2.0
Requires-Dist: tomli>=2.0.0; python_version < "3.11"
Provides-Extra: dev
Requires-Dist: pytest>=7.0; extra == "dev"
Requires-Dist: pytest-cov>=4.0; extra == "dev"
Requires-Dist: mypy>=1.0; extra == "dev"
Requires-Dist: flake8>=6.0; extra == "dev"
Provides-Extra: gui
Requires-Dist: ttkbootstrap>=1.10.1; extra == "gui"
Requires-Dist: pygments>=2.0; extra == "gui"
Dynamic: license-file
